scrubadub/__init__.py
scrubadub/comparison.py
scrubadub/exceptions.py
scrubadub/scrubbers.py
scrubadub/utils.py
scrubadub/detectors/__init__.py
scrubadub/detectors/base.py
scrubadub/detectors/catalogue.py
scrubadub/detectors/credential.py
scrubadub/detectors/credit_card.py
scrubadub/detectors/date_of_birth.py
scrubadub/detectors/drivers_licence.py
scrubadub/detectors/email.py
scrubadub/detectors/phone.py
scrubadub/detectors/postalcode.py
scrubadub/detectors/skype.py
scrubadub/detectors/tagged.py
scrubadub/detectors/text_blob.py
scrubadub/detectors/twitter.py
scrubadub/detectors/url.py
scrubadub/detectors/user_supplied.py
scrubadub/detectors/vehicle_licence_plate.py
scrubadub/detectors/en_GB/__init__.py
scrubadub/detectors/en_GB/national_insurance_number.py
scrubadub/detectors/en_GB/tax_reference_number.py
scrubadub/detectors/en_US/__init__.py
scrubadub/detectors/en_US/social_security_number.py
scrubadub/filth/__init__.py
scrubadub/filth/address.py
scrubadub/filth/base.py
scrubadub/filth/credential.py
scrubadub/filth/credit_card.py
scrubadub/filth/date_of_birth.py
scrubadub/filth/drivers_licence.py
scrubadub/filth/email.py
scrubadub/filth/location.py
scrubadub/filth/name.py
scrubadub/filth/organization.py
scrubadub/filth/phone.py
scrubadub/filth/postalcode.py
scrubadub/filth/skype.py
scrubadub/filth/tagged.py
scrubadub/filth/twitter.py
scrubadub/filth/url.py
scrubadub/filth/vehicle_licence_plate.py
scrubadub/filth/en_GB/__init__.py
scrubadub/filth/en_GB/national_insurance_number.py
scrubadub/filth/en_GB/tax_reference_number.py
scrubadub/filth/en_US/__init__.py
scrubadub/filth/en_US/social_security_number.py
scrubadub/post_processors/__init__.py
scrubadub/post_processors/base.py
scrubadub/post_processors/catalogue.py
scrubadub/post_processors/filth_replacer.py
scrubadub/post_processors/prefix_suffix.py
scrubadub/post_processors/remover.py
scrubadub-2.0.1.dist-info/LICENSE
scrubadub-2.0.1.dist-info/METADATA
scrubadub-2.0.1.dist-info/WHEEL
scrubadub-2.0.1.dist-info/top_level.txt
scrubadub-2.0.1.dist-info/RECORD
