Metadata-Version: 2.1
Name: scrubadub
Version: 2.0.1
Summary: Clean personally identifiable information from dirty dirty text.
Home-page: https://github.com/LeapBeyond/scrubadub
Download-URL: https://github.com/LeapBeyond/scrubadub/archives/master
Author: Dean Malmgren
Author-email: dean.malmgren@datascopeanalytics.com
License: MIT
Classifier: Intended Audience :: Developers
Classifier: Development Status :: 5 - Production/Stable
Classifier: License :: OSI Approved :: Apache Software License
Classifier: Natural Language :: English
Classifier: Programming Language :: Python
Classifier: Programming Language :: Python :: 3
Classifier: Programming Language :: Python :: 3.6
Classifier: Programming Language :: Python :: 3.7
Classifier: Programming Language :: Python :: 3.8
Classifier: Programming Language :: Python :: 3.9
Classifier: Topic :: Software Development :: Libraries
Classifier: Topic :: Scientific/Engineering :: Information Analysis
Classifier: Topic :: Text Processing
Classifier: Topic :: Utilities
License-File: LICENSE
